{
    "id":  "relationship.drop-burston-prime-barrel-lith-f2-relic-flawless",
    "type":  "wfcd_drop",
    "from":  "source.lith-f2-relic-flawless",
    "to":  "part.burston-prime-barrel",
    "summary":  "Lith F2 Relic (Flawless) can drop Burston Prime Barrel.",
    "conditions":  {

                   },
    "values":  {
                   "location":  "Lith F2 Relic (Flawless)",
                   "chance":  17,
                   "rarity":  "Uncommon",
                   "rewardType":  "Burston Prime Barrel",
                   "parentId":  "weapon.burston-prime"
               },
    "tags":  [
                 "drop",
                 "wfcd-generated"
             ],
    "sources":  [
                    {
                        "type":  "wfcd-generated",
                        "value":  "drop:weapon.burston-prime"
                    }
                ]
}
