{
    "id":  "relationship.drop-daikyu-prime-grip-neo-d10-relic-flawless",
    "type":  "wfcd_drop",
    "from":  "source.neo-d10-relic-flawless",
    "to":  "part.daikyu-prime-grip",
    "summary":  "Neo D10 Relic (Flawless) can drop Daikyu Prime Grip.",
    "conditions":  {

                   },
    "values":  {
                   "location":  "Neo D10 Relic (Flawless)",
                   "chance":  6,
                   "rarity":  "Rare",
                   "rewardType":  "Daikyu Prime Grip",
                   "parentId":  "weapon.daikyu-prime"
               },
    "tags":  [
                 "drop",
                 "wfcd-generated"
             ],
    "sources":  [
                    {
                        "type":  "wfcd-generated",
                        "value":  "drop:weapon.daikyu-prime"
                    }
                ]
}
