{
    "id":  "relationship.drop-spectra-vandal-chassis-veil-proxima-nsu-grid-caches-rotation-b",
    "type":  "wfcd_drop",
    "from":  "activity.veil-proxima-nsu-grid",
    "to":  "part.spectra-vandal-chassis",
    "summary":  "Veil Proxima/Nsu Grid (Caches), Rotation B can drop Spectra Vandal Chassis.",
    "conditions":  {
                       "rotation":  "B"
                   },
    "values":  {
                   "location":  "Veil Proxima/Nsu Grid (Caches), Rotation B",
                   "chance":  6.52,
                   "rarity":  "Rare",
                   "rewardType":  "Spectra Vandal Chassis",
                   "parentId":  "weapon.spectra-vandal",
                   "rawLocation":  "Veil Proxima/Nsu Grid (Caches), Rotation B",
                   "locationPlanet":  "Veil Proxima",
                   "locationNode":  "Nsu Grid",
                   "missionType":  "Caches"
               },
    "tags":  [
                 "drop",
                 "wfcd-generated",
                 "activity-normalized"
             ],
    "sources":  [
                    {
                        "type":  "wfcd-generated",
                        "value":  "drop:weapon.spectra-vandal"
                    }
                ]
}
