{
    "id":  "relationship.drop-bronco-prime-receiver-lith-l7-relic-exceptional",
    "type":  "wfcd_drop",
    "from":  "source.lith-l7-relic-exceptional",
    "to":  "part.bronco-prime-receiver",
    "summary":  "Lith L7 Relic (Exceptional) can drop Bronco Prime Receiver.",
    "conditions":  {

                   },
    "values":  {
                   "location":  "Lith L7 Relic (Exceptional)",
                   "chance":  23.33,
                   "rarity":  "Uncommon",
                   "rewardType":  "Bronco Prime Receiver",
                   "parentId":  "weapon.bronco-prime"
               },
    "tags":  [
                 "drop",
                 "wfcd-generated"
             ],
    "sources":  [
                    {
                        "type":  "wfcd-generated",
                        "value":  "drop:weapon.bronco-prime"
                    }
                ]
}
