{
    "id":  "relationship.drop-paris-prime-string-axi-s20-relic-flawless",
    "type":  "wfcd_drop",
    "from":  "source.axi-s20-relic-flawless",
    "to":  "part.paris-prime-string",
    "summary":  "Axi S20 Relic (Flawless) can drop Paris Prime String.",
    "conditions":  {

                   },
    "values":  {
                   "location":  "Axi S20 Relic (Flawless)",
                   "chance":  20,
                   "rarity":  "Uncommon",
                   "rewardType":  "Paris Prime String",
                   "parentId":  "weapon.paris-prime"
               },
    "tags":  [
                 "drop",
                 "wfcd-generated"
             ],
    "sources":  [
                    {
                        "type":  "wfcd-generated",
                        "value":  "drop:weapon.paris-prime"
                    }
                ]
}
