{
    "id":  "relationship.drop-frost-prime-chassis-neo-b8-relic-radiant",
    "type":  "wfcd_drop",
    "from":  "source.neo-b8-relic-radiant",
    "to":  "part.frost-prime-chassis",
    "summary":  "Neo B8 Relic (Radiant) can drop Frost Prime Chassis Blueprint.",
    "conditions":  {

                   },
    "values":  {
                   "location":  "Neo B8 Relic (Radiant)",
                   "chance":  16.67,
                   "rarity":  "Uncommon",
                   "rewardType":  "Frost Prime Chassis Blueprint",
                   "parentId":  "warframe.frost-prime"
               },
    "tags":  [
                 "drop",
                 "wfcd-generated"
             ],
    "sources":  [
                    {
                        "type":  "wfcd-generated",
                        "value":  "drop:warframe.frost-prime"
                    }
                ]
}
