{
    "id":  "relationship.drop-banshee-prime-chassis-neo-b1-relic-flawless",
    "type":  "wfcd_drop",
    "from":  "source.neo-b1-relic-flawless",
    "to":  "part.banshee-prime-chassis",
    "summary":  "Neo B1 Relic (Flawless) can drop Banshee Prime Chassis Blueprint.",
    "conditions":  {

                   },
    "values":  {
                   "location":  "Neo B1 Relic (Flawless)",
                   "chance":  6,
                   "rarity":  "Rare",
                   "rewardType":  "Banshee Prime Chassis Blueprint",
                   "parentId":  "warframe.banshee-prime"
               },
    "tags":  [
                 "drop",
                 "wfcd-generated"
             ],
    "sources":  [
                    {
                        "type":  "wfcd-generated",
                        "value":  "drop:warframe.banshee-prime"
                    }
                ]
}
