{
    "id":  "relationship.drop-voruna-prime-blueprint-axi-v14-relic-radiant",
    "type":  "wfcd_drop",
    "from":  "source.axi-v14-relic-radiant",
    "to":  "part.voruna-prime-blueprint",
    "summary":  "Axi V14 Relic (Radiant) can drop Voruna Prime Blueprint.",
    "conditions":  {

                   },
    "values":  {
                   "location":  "Axi V14 Relic (Radiant)",
                   "chance":  10,
                   "rarity":  "Uncommon",
                   "rewardType":  "Voruna Prime Blueprint",
                   "parentId":  "warframe.voruna-prime"
               },
    "tags":  [
                 "drop",
                 "wfcd-generated"
             ],
    "sources":  [
                    {
                        "type":  "wfcd-generated",
                        "value":  "drop:warframe.voruna-prime"
                    }
                ]
}
