{
    "id":  "activity.quest-sands-of-inaros",
    "sources":  [
                    {
                        "type":  "static-import",
                        "value":  "imports/static/source-snapshots/wfcd/wfcd-activities.json"
                    }
                ],
    "name":  "Sands Of Inaros",
    "subCategory":  "quest",
    "notes":  [
                  "Normalized from static import source.",
                  "Converted from WFCD Quests.json."
              ],
    "mechanics":  {
                      "wiki":  {
                                   "thumbnail":  null,
                                   "url":  null,
                                   "imageName":  "sands-of-inaros-76a13d5b47.png",
                                   "available":  null
                               },
                      "drops":  [
                                    null
                                ],
                      "crafting":  {
                                       "buildTime":  21600,
                                       "buildPrice":  5000,
                                       "buildQuantity":  1,
                                       "components":  [
                                                          {
                                                              "name":  "Blueprint",
                                                              "uniqueName":  "/Lotus/Types/Keys/MummyQuestKeyBlueprint",
                                                              "itemCount":  1,
                                                              "type":  null,
                                                              "tradable":  false,
                                                              "drops":  [

                                                                        ]
                                                          },
                                                          {
                                                              "name":  "Nano Spores",
                                                              "uniqueName":  "/Lotus/Types/Items/MiscItems/Nanospores",
                                                              "itemCount":  5000,
                                                              "type":  "Resource",
                                                              "tradable":  false,
                                                              "drops":  [

                                                                        ]
                                                          },
                                                          {
                                                              "name":  "Nitain Extract",
                                                              "uniqueName":  "/Lotus/Types/Items/MiscItems/Alertium",
                                                              "itemCount":  1,
                                                              "type":  null,
                                                              "tradable":  false,
                                                              "drops":  [

                                                                        ]
                                                          },
                                                          {
                                                              "name":  "Oxium",
                                                              "uniqueName":  "/Lotus/Types/Items/MiscItems/OxiumAlloy",
                                                              "itemCount":  400,
                                                              "type":  "Resource",
                                                              "tradable":  false,
                                                              "drops":  [

                                                                        ]
                                                          }
                                                      ],
                                       "skipBuildTimePrice":  15,
                                       "consumeOnBuild":  true
                                   },
                      "type":  "Key"
                  },
    "aliases":  [
                    "/Lotus/Types/Keys/MummyQuest/MummyQuestKeyChain"
                ],
    "tags":  [
                 "activity",
                 "quest"
             ],
    "category":  "activity",
    "relationships":  [

                      ],
    "description":  "Help Baro Ki\u0027Teer raid an ancient Martian tomb for a mysterious treasure.",
    "release":  {

                },
    "summary":  "Help Baro Ki\u0027Teer raid an ancient Martian tomb for a mysterious treasure.",
    "stats":  {
                  "tradable":  false,
                  "masterable":  false
              }
}
