{
    "id":  "part.twin-rogga-kuva",
    "name":  "Kuva",
    "category":  "item_part",
    "subCategory":  "component",
    "aliases":  [

                ],
    "summary":  "Kuva is an exceedingly rare red fluid coveted by the Grineer Queens. It can be obtained in Kuva Missions, and is used to Cycle Rivens or build rare blueprints.\n\nLocation: Kuva Siphon Missions and Taveuni (Kuva Fortress)",
    "description":  "Kuva is an exceedingly rare red fluid coveted by the Grineer Queens. It can be obtained in Kuva Missions, and is used to Cycle Rivens or build rare blueprints.\n\nLocation: Kuva Siphon Missions and Taveuni (Kuva Fortress)",
    "stats":  {

              },
    "mechanics":  {

                  },
    "relationships":  [
                          "weapon.twin-rogga"
                      ],
    "release":  {

                },
    "tags":  [
                 "part",
                 "wfcd-generated"
             ],
    "notes":  [
                  "Generated from WFCD component or relic reward data."
              ],
    "sources":  [
                    {
                        "type":  "wfcd-generated",
                        "value":  "component:weapon.twin-rogga"
                    }
                ]
}
