{
    "id":  "relationship.relic-reward-meso-f3-exceptional-glaive-prime-disc",
    "type":  "relic_reward",
    "from":  "relic.meso-f3-exceptional",
    "to":  "part.glaive-prime-disc",
    "summary":  "relic.meso-f3-exceptional contains Glaive Prime Disc as a reward.",
    "conditions":  {
                       "rarity":  "Uncommon"
                   },
    "values":  {
                   "chance":  13,
                   "rewardName":  "Glaive Prime Disc"
               },
    "tags":  [
                 "relic",
                 "reward",
                 "wfcd-generated"
             ],
    "sources":  [
                    {
                        "type":  "wfcd-generated",
                        "value":  "relic:relic.meso-f3-exceptional"
                    }
                ]
}
