{
    "id":  "relationship.relic-reward-neo-n20-intact-tenora-prime-blueprint",
    "type":  "relic_reward",
    "from":  "relic.neo-n20-intact",
    "to":  "part.tenora-prime-blueprint",
    "summary":  "relic.neo-n20-intact contains Tenora Prime Blueprint as a reward.",
    "conditions":  {
                       "rarity":  "Uncommon"
                   },
    "values":  {
                   "chance":  25.33,
                   "rewardName":  "Tenora Prime Blueprint"
               },
    "tags":  [
                 "relic",
                 "reward",
                 "wfcd-generated"
             ],
    "sources":  [
                    {
                        "type":  "wfcd-generated",
                        "value":  "relic:relic.neo-n20-intact"
                    }
                ]
}
