{
    "id":  "relationship.relic-reward-neo-t8-radiant-vasto-prime-receiver",
    "type":  "relic_reward",
    "from":  "relic.neo-t8-radiant",
    "to":  "part.vasto-prime-receiver",
    "summary":  "relic.neo-t8-radiant contains Vasto Prime Receiver as a reward.",
    "conditions":  {
                       "rarity":  "Uncommon"
                   },
    "values":  {
                   "chance":  16.67,
                   "rewardName":  "Vasto Prime Receiver"
               },
    "tags":  [
                 "relic",
                 "reward",
                 "wfcd-generated"
             ],
    "sources":  [
                    {
                        "type":  "wfcd-generated",
                        "value":  "relic:relic.neo-t8-radiant"
                    }
                ]
}
