{
    "id":  "relationship.relic-reward-lith-n6-exceptional-stradavar-prime-barrel",
    "type":  "relic_reward",
    "from":  "relic.lith-n6-exceptional",
    "to":  "part.stradavar-prime-barrel",
    "summary":  "relic.lith-n6-exceptional contains Stradavar Prime Barrel as a reward.",
    "conditions":  {
                       "rarity":  "Uncommon"
                   },
    "values":  {
                   "chance":  13,
                   "rewardName":  "Stradavar Prime Barrel"
               },
    "tags":  [
                 "relic",
                 "reward",
                 "wfcd-generated"
             ],
    "sources":  [
                    {
                        "type":  "wfcd-generated",
                        "value":  "relic:relic.lith-n6-exceptional"
                    }
                ]
}
