{
    "id":  "relationship.relic-reward-lith-t12-radiant-velox-prime-receiver",
    "type":  "relic_reward",
    "from":  "relic.lith-t12-radiant",
    "to":  "part.velox-prime-receiver",
    "summary":  "relic.lith-t12-radiant contains Velox Prime Receiver as a reward.",
    "conditions":  {
                       "rarity":  "Uncommon"
                   },
    "values":  {
                   "chance":  16.67,
                   "rewardName":  "Velox Prime Receiver"
               },
    "tags":  [
                 "relic",
                 "reward",
                 "wfcd-generated"
             ],
    "sources":  [
                    {
                        "type":  "wfcd-generated",
                        "value":  "relic:relic.lith-t12-radiant"
                    }
                ]
}
