{
    "id":  "relationship.relic-reward-lith-k4-flawless-nova-prime-neuroptics-blueprint",
    "type":  "relic_reward",
    "from":  "relic.lith-k4-flawless",
    "to":  "part.nova-prime-neuroptics-blueprint",
    "summary":  "relic.lith-k4-flawless contains Nova Prime Neuroptics Blueprint as a reward.",
    "conditions":  {
                       "rarity":  "Uncommon"
                   },
    "values":  {
                   "chance":  20,
                   "rewardName":  "Nova Prime Neuroptics Blueprint"
               },
    "tags":  [
                 "relic",
                 "reward",
                 "wfcd-generated"
             ],
    "sources":  [
                    {
                        "type":  "wfcd-generated",
                        "value":  "relic:relic.lith-k4-flawless"
                    }
                ]
}
