{
    "id":  "relationship.relic-reward-neo-f1-flawless-bo-prime-handle",
    "type":  "relic_reward",
    "from":  "relic.neo-f1-flawless",
    "to":  "part.bo-prime-handle",
    "summary":  "relic.neo-f1-flawless contains Bo Prime Handle as a reward.",
    "conditions":  {
                       "rarity":  "Uncommon"
                   },
    "values":  {
                   "chance":  17,
                   "rewardName":  "Bo Prime Handle"
               },
    "tags":  [
                 "relic",
                 "reward",
                 "wfcd-generated"
             ],
    "sources":  [
                    {
                        "type":  "wfcd-generated",
                        "value":  "relic:relic.neo-f1-flawless"
                    }
                ]
}
