{
    "id":  "mod.gleaming-blight",
    "sources":  [
                    {
                        "type":  "static-import",
                        "value":  "imports/static/source-snapshots/wfcd/wfcd-mods.json"
                    }
                ],
    "name":  "Gleaming Blight",
    "subCategory":  "dark-dagger",
    "notes":  [
                  "Normalized from static import source.",
                  "Converted from WFCD Mods.json."
              ],
    "mechanics":  {
                      "topRankStats":  [
                                           "+100% Status Chance",
                                           "+1 \u0027Blight\u0027"
                                       ],
                      "type":  "Melee Mod",
                      "drops":  [
                                    {
                                        "location":  "Red Veil, Revered",
                                        "type":  "Gleaming Blight (Dark Dagger)",
                                        "chance":  100,
                                        "rarity":  "Common"
                                    }
                                ],
                      "isAugment":  null,
                      "levelStats":  [
                                         "+25% Status Chance",
                                         "+0.3 \u0027Blight\u0027",
                                         "+50% Status Chance",
                                         "+0.5 \u0027Blight\u0027",
                                         "+75% Status Chance",
                                         "+0.8 \u0027Blight\u0027",
                                         "+100% Status Chance",
                                         "+1 \u0027Blight\u0027"
                                     ],
                      "wiki":  {
                                   "thumbnail":  "https://wiki.warframe.com/images/GleamingBlightMod.png?09620",
                                   "url":  "https://wiki.warframe.com/w/Gleaming_Blight",
                                   "imageName":  "DarkDagger.jpg",
                                   "available":  true
                               }
                  },
    "aliases":  [
                    "/Lotus/Upgrades/Mods/Syndicate/DarkDaggerMod"
                ],
    "tags":  [
                 "mod"
             ],
    "category":  "mod",
    "relationships":  [

                      ],
    "description":  "+100% Status Chance +1 \u0027Blight\u0027",
    "release":  {
                    "releaseDate":  "2014-10-24",
                    "introduced":  {
                                       "date":  "2014-10-24",
                                       "parent":  "15.0",
                                       "url":  "https://wiki.warframe.com/w/Update_15%23Update_15.0",
                                       "name":  "Update 15.0",
                                       "aliases":  [
                                                       "15.0",
                                                       "15",
                                                       "Archwing",
                                                       "Update 15"
                                                   ]
                                   }
                },
    "summary":  "+100% Status Chance +1 \u0027Blight\u0027",
    "stats":  {
                  "baseDrain":  4,
                  "tradable":  true,
                  "compatName":  "Dark Dagger",
                  "masterable":  false,
                  "polarity":  "naramon",
                  "fusionLimit":  3,
                  "isPrime":  false,
                  "rarity":  "Rare",
                  "transmutable":  false
              }
}
