{
    "id":  "mod.meteoric-dash",
    "sources":  [
                    {
                        "type":  "static-import",
                        "value":  "imports/static/source-snapshots/wfcd/wfcd-mods.json"
                    }
                ],
    "name":  "Meteoric Dash",
    "subCategory":  "mod",
    "notes":  [
                  "Normalized from static import source.",
                  "Converted from WFCD Mods.json."
              ],
    "mechanics":  {
                      "topRankStats":  [
                                           "Void Sling deals 400 Extra Damage to enemies."
                                       ],
                      "type":  "Focus Way",
                      "drops":  [
                                    null
                                ],
                      "isAugment":  null,
                      "levelStats":  [
                                         "Void Sling deals 100 Extra Damage to enemies.",
                                         "Void Sling deals 200 Extra Damage to enemies.",
                                         "Void Sling deals 300 Extra Damage to enemies.",
                                         "Void Sling deals 400 Extra Damage to enemies."
                                     ],
                      "wiki":  {
                                   "thumbnail":  null,
                                   "url":  null,
                                   "imageName":  "meteoric-dash-9859e9f6d9.jpg",
                                   "available":  null
                               }
                  },
    "aliases":  [
                    "/Lotus/Upgrades/Focus/Attack/Active/DashDamageFocusUpgrade"
                ],
    "tags":  [
                 "mod"
             ],
    "category":  "mod",
    "relationships":  [

                      ],
    "description":  "Void Sling deals 400 Extra Damage to enemies.",
    "release":  {
                    "releaseDate":  null,
                    "introduced":  null
                },
    "summary":  "Void Sling deals 400 Extra Damage to enemies.",
    "stats":  {
                  "baseDrain":  4,
                  "tradable":  false,
                  "compatName":  null,
                  "masterable":  false,
                  "polarity":  "madurai",
                  "fusionLimit":  3,
                  "isPrime":  false,
                  "rarity":  "Rare",
                  "transmutable":  null
              }
}
