{
    "id":  "mod.mountain-s-edge",
    "sources":  [
                    {
                        "type":  "static-import",
                        "value":  "imports/static/source-snapshots/wfcd/wfcd-mods.json"
                    }
                ],
    "name":  "Mountain\u0027s Edge",
    "subCategory":  "dual-nikanas",
    "notes":  [
                  "Normalized from static import source.",
                  "Converted from WFCD Mods.json."
              ],
    "mechanics":  {
                      "topRankStats":  [

                                       ],
                      "type":  "Stance Mod",
                      "drops":  [
                                    null
                                ],
                      "isAugment":  null,
                      "levelStats":  [
                                         null
                                     ],
                      "wiki":  {
                                   "thumbnail":  "https://wiki.warframe.com/images/Mountain%27sEdgeMod.png?2a794",
                                   "url":  "https://wiki.warframe.com/w/Mountain\u0027s_Edge",
                                   "imageName":  "DualKatanaCmbOne.jpg",
                                   "available":  true
                               }
                  },
    "aliases":  [
                    "/Lotus/Weapons/Tenno/Melee/MeleeTrees/DualKatanaCmbOneMeleeTree"
                ],
    "tags":  [
                 "mod"
             ],
    "category":  "mod",
    "relationships":  [

                      ],
    "description":  "Mountain\u0027s Edge imported from WFCD static data.",
    "release":  {
                    "releaseDate":  "2023-04-26",
                    "introduced":  {
                                       "date":  "2023-04-26",
                                       "parent":  "33.0",
                                       "url":  "https://wiki.warframe.com/w/Update_33%23Update_33.0",
                                       "name":  "Update 33.0",
                                       "aliases":  [
                                                       "33",
                                                       "33.0"
                                                   ]
                                   }
                },
    "summary":  "Mountain\u0027s Edge imported from WFCD static data.",
    "stats":  {
                  "baseDrain":  -2,
                  "tradable":  true,
                  "compatName":  "Dual Nikanas",
                  "masterable":  false,
                  "polarity":  "naramon",
                  "fusionLimit":  3,
                  "isPrime":  false,
                  "rarity":  "Uncommon",
                  "transmutable":  false
              }
}
